cosinnus_etherpad/__init__.py
cosinnus_etherpad/admin.py
cosinnus_etherpad/apps.py
cosinnus_etherpad/conf.py
cosinnus_etherpad/cosinnus_app.py
cosinnus_etherpad/cosinnus_notifications.py
cosinnus_etherpad/dashboard.py
cosinnus_etherpad/filters.py
cosinnus_etherpad/forms.py
cosinnus_etherpad/hooks.py
cosinnus_etherpad/managers.py
cosinnus_etherpad/models.py
cosinnus_etherpad/notify.py
cosinnus_etherpad/search_indexes.py
cosinnus_etherpad/urls.py
cosinnus_etherpad/views.py
cosinnus_etherpad/locale/de/LC_MESSAGES/django.mo
cosinnus_etherpad/locale/de/LC_MESSAGES/django.po
cosinnus_etherpad/locale/en/LC_MESSAGES/django.mo
cosinnus_etherpad/locale/en/LC_MESSAGES/django.po
cosinnus_etherpad/locale/fr/LC_MESSAGES/django.mo
cosinnus_etherpad/locale/fr/LC_MESSAGES/django.po
cosinnus_etherpad/locale/ru/LC_MESSAGES/django.mo
cosinnus_etherpad/locale/ru/LC_MESSAGES/django.po
cosinnus_etherpad/locale/uk/LC_MESSAGES/django.mo
cosinnus_etherpad/locale/uk/LC_MESSAGES/django.po
cosinnus_etherpad/migrations/0001_initial.py
cosinnus_etherpad/migrations/0002_auto_20151104_1711.py
cosinnus_etherpad/migrations/0003_auto_20160125_1339.py
cosinnus_etherpad/migrations/0004_auto_20160511_1852.py
cosinnus_etherpad/migrations/0005_auto_20161103_1520.py
cosinnus_etherpad/migrations/0006_etherpad_last_accessed.py
cosinnus_etherpad/migrations/__init__.py
cosinnus_etherpad/static/css/cosinnus_etherpad/cosinnus_etherpad.css
cosinnus_etherpad/static/js/cosinnus_etherpad/cosinnus_etherpad.js
cosinnus_etherpad/templates/cosinnus_etherpad/attached_etherpads.html
cosinnus_etherpad/templates/cosinnus_etherpad/attached_object_select_pill.html
cosinnus_etherpad/templates/cosinnus_etherpad/base.html
cosinnus_etherpad/templates/cosinnus_etherpad/etherpad_detail.html
cosinnus_etherpad/templates/cosinnus_etherpad/etherpad_edit.html
cosinnus_etherpad/templates/cosinnus_etherpad/etherpad_list.html
cosinnus_etherpad-0.6.dev20180515152125.dist-info/DESCRIPTION.rst
cosinnus_etherpad-0.6.dev20180515152125.dist-info/METADATA
cosinnus_etherpad-0.6.dev20180515152125.dist-info/RECORD
cosinnus_etherpad-0.6.dev20180515152125.dist-info/WHEEL
cosinnus_etherpad-0.6.dev20180515152125.dist-info/metadata.json
cosinnus_etherpad-0.6.dev20180515152125.dist-info/top_level.txt
